zenodo_search/__init__.py
zenodo_search/_version.py
zenodo_search/utils.py
zenodo_search/zsearch.py
zenodo_search-0.2.1.dist-info/LICENSE
zenodo_search-0.2.1.dist-info/METADATA
zenodo_search-0.2.1.dist-info/WHEEL
zenodo_search-0.2.1.dist-info/top_level.txt
zenodo_search-0.2.1.dist-info/RECORD
