Metadata-Version: 2.1
Name: zenodo-search
Version: 0.2.1
Summary: Perform Query on Zenodo.
Home-page: https://github.com/matthiasprobst/zenodo_search
Author: Matthias Probst
Author-email: matth.probst@gmail.com
Classifier: Programming Language :: Python :: 3
Classifier: Programming Language :: Python :: 3.8
Classifier: Programming Language :: Python :: 3.9
Classifier: Programming Language :: Python :: 3.10
Classifier: Programming Language :: Python :: 3.11
Classifier: License :: OSI Approved :: MIT License
Classifier: Operating System :: OS Independent
Classifier: Development Status :: 4 - Beta
Requires-Python: >=3.8
License-File: LICENSE
Requires-Dist: requests
